<?xml version="1.0" encoding="UTF-8"?>
<!--
    Licensed Materials - Property of IBM
    5725-I43 (C) Copyright IBM Corp. 2011, 2013. All Rights Reserved.
    US Government Users Restricted Rights - Use, duplication or
    disclosure restricted by GSA ADP Schedule Contract with IBM Corp.
-->
<nativeAndroidApp id="AndroidAPI" platformVersion="6.3.0.00.20150106-1717"
	version="1.0" xmlns="http://www.worklight.com/native-android-descriptor">
	
	<displayName>AndroidAPI</displayName>
	<description>AndroidAPI</description>
	<publicSigningKey></publicSigningKey>
	<packageName></packageName>
		
</nativeAndroidApp>